Workbook

Sheet How to use
A1: Binggio 0.1 user acceptance test
A3: What this is | B3: 78 end-to-end cases covering install, the app, the sample bank, adding data, discovery, onboarding, review, data changes, asking, safety, performance and the screens. Release when every P1 case passes.
A4: The agent | B4: python uat\run_uat.py runs every case it can on a fresh simulated machine and fills in "Agent result" and "Agent finding" in a copy of this workbook (uat\reports\UAT_results_<time>.xlsx). Add --with-model for questions in your own words, --sqlserver "host=localhost;database=master;windows" for SQL Server.
A5: Agent result | B5: PASS: checked against independent counts or exact values. FAIL: clearly wrong. AMBIGUOUS: the agent cannot decide; you decide. NOT RUN: needs a server, Playwright or a model key on this PC.
A6: What you fill in | B6: Only the yellow columns: Your result (choose from the list), Tester, Date, Notes. Give every AMBIGUOUS case a verdict, and re-test FAIL cases after the fix.
A7: Your result | B7: PASS, FAIL, BLOCKED (cannot be tested yet) or N/A (does not apply to this release).
A8: Example row | B8: Your result: FAIL · Tester: Ashish · Date: 30-Oct-2026 · Notes: Refresh listed "accounts, loans" as changed but only accounts changed.
A9: Release rule | B9: All P1 cases PASS (by the agent or by you), no FAIL left open, every AMBIGUOUS case decided. The Summary tab counts these.
A11: Columns to fill in | B11: Yellow
A12: Filled by the agent | B12: Grey

Sheet UAT cases
A1: ID | B1: Area | C1: Priority | D1: Test | E1: Steps | F1: Expected result | G1: How it is run | H1: How the agent decides | I1: Agent hands it to you when | J1: Agent result | K1: Agent finding | L1: Your result | M1: Tester | N1: Date | O1: Notes
A2: INS-01 | B2: Install | C2: P1 | D2: Install from the built package into a clean Python | E2: 1. Build the wheel from a clean copy of the source 2. Create a new virtual environment 3. pip install the wheel | F2: Install succeeds with no extra dependencies | G2: Agent | H2: pip exit code 0; binggio has no required dependencies | I2: -
A3: INS-02 | B3: Install | C3: P1 | D3: Installed files are exactly the source | E3: Compare every installed file with the source tree | F3: Every file identical; none missing (UI page and sample bank included) | G3: Agent | H3: byte comparison of all files | I3: -
A4: INS-03 | B4: Install | C4: P1 | D4: binggio --version and --help | E4: Run binggio --version, then binggio --help | F4: Version 0.1.0 printed; help lists ui, onboard, ask | G4: Agent | H4: exit code and text | I4: -
A5: INS-04 | B5: Install | C5: P1 | D5: python -m binggio works when the command is not on PATH | E5: Run python -m binggio --version | F5: Same output as binggio --version | G5: Agent | H5: exit code and text | I5: -
A6: INS-05 | B6: Install | C6: P2 | D6: Excel extra installs | E6: pip install openpyxl into the environment (binggio[excel]) | F6: Excel support available | G6: Agent | H6: import works after install | I6: install fails because there is no internet (cannot tell a packaging fault from a network fault)
A7: LIC-01 | B7: Install | C7: P1 | D7: Licence is the official AGPL-3.0 text and the package declares it | E7: Check LICENSE in the source and the installed package metadata | F7: LICENSE is the unchanged GNU AGPL v3 text; metadata says AGPL-3.0-or-later; source files carry the SPDX header | G7: Agent | H7: file heading, version line and length; metadata; headers on every source file | I7: -
A8: INS-06 | B8: Install | C8: P1 | D8: Commands outside a workspace explain what to do | E8: In an empty folder run binggio status | F8: Clear message "No Binggio workspace found ... Run: binggio init"; exit code 2, no traceback | G8: Agent | H8: exit code 2 and message; no "Traceback" in output | I8: -
A9: APP-01 | B9: App | C9: P1 | D9: binggio ui starts and prints its address | E9: Run binggio ui --no-browser in a folder that is not a workspace | F9: Address http://127.0.0.1:<port>/ printed within 10 s; start screen served | G9: Agent | H9: address printed; page contains the app | I9: starts but takes 10-30 s
A10: APP-02 | B10: App | C10: P1 | D10: API refuses requests without the session token | E10: Call the API with no token and a wrong token | F10: HTTP 403 both times | G10: Agent | H10: status codes | I10: -
A11: APP-03 | B11: App | C11: P1 | D11: API refuses another host name (DNS rebinding) | E11: Call the API with Host: evil.example | F11: HTTP 403 | G11: Agent | H11: status code | I11: -
A12: APP-04 | B12: App | C12: P1 | D12: Start screen: create the sample bank | E12: Choose a folder, name it, click Create the sample bank | F12: Sample bank created; app opens on Ask | G12: Agent | H12: workspace created; status shows 63 answerable tables | I12: -
A13: APP-05 | B13: App | C13: P2 | D13: Start screen: open an existing workspace and the recent list | E13: Open a workspace by folder; restart the app; check Recent | F13: Workspace opens; it appears in Recent after restart | G13: Agent | H13: open succeeds; recent list contains it | I13: -
... A79: UI-05 | B79: Screens | C79: P2 | D79: Keyboard: the question box and dialogs | E79: Press Enter to ask; Esc closes a dialog | F79: Both work | G79: Agent + browser | H79: answer appears; dialog closes | I79: -

Sheet Summary
A1: Summary
A2: Counts update as results are entered. "Decided" = your result if given, otherwise the agent's PASS or FAIL.
A4: Area | B4: Cases | C4: P1 | D4: Agent PASS | E4: Agent FAIL | F4: Ambiguous | G4: Not run | H4: Your PASS | I4: Your FAIL
A5: Install | B5: =COUNTIF('UAT cases'!$B$2:$B$79,$A5) | C5: =COUNTIFS('UAT cases'!$B$2:$B$79,$A5,'UAT cases'!$C$2:$C$79,"P1") | D5: =COUNTIFS('UAT cases'!$B$2:$B$79,$A5,'UAT cases'!$J$2:$J$79,"PASS") | E5: =COUNTIFS('UAT cases'!$B$2:$B$79,$A5,'UAT cases'!$J$2:$J$79,"FAIL") | F5: =COUNTIFS('UAT cases'!$B$2:$B$79,$A5,'UAT cases'!$J$2:$J$79,"AMBIGUOUS") | G5: =COUNTIFS('UAT cases'!$B$2:$B$79,$A5,'UAT cases'!$J$2:$J$79,"NOT RUN") | H5: =COUNTIFS('UAT cases'!$B$2:$B$79,$A5,'UAT cases'!$L$2:$L$79,"PASS") | I5: =COUNTIFS('UAT cases'!$B$2:$B$79,$A5,'UAT cases'!$L$2:$L$79,"FAIL")
A6: App | B6: =COUNTIF('UAT cases'!$B$2:$B$79,$A6) | C6: =COUNTIFS('UAT cases'!$B$2:$B$79,$A6,'UAT cases'!$C$2:$C$79,"P1") | D6: =COUNTIFS('UAT cases'!$B$2:$B$79,$A6,'UAT cases'!$J$2:$J$79,"PASS") | E6: =COUNTIFS('UAT cases'!$B$2:$B$79,$A6,'UAT cases'!$J$2:$J$79,"FAIL") | F6: =COUNTIFS('UAT cases'!$B$2:$B$79,$A6,'UAT cases'!$J$2:$J$79,"AMBIGUOUS") | G6: =COUNTIFS('UAT cases'!$B$2:$B$79,$A6,'UAT cases'!$J$2:$J$79,"NOT RUN") | H6: =COUNTIFS('UAT cases'!$B$2:$B$79,$A6,'UAT cases'!$L$2:$L$79,"PASS") | I6: =COUNTIFS('UAT cases'!$B$2:$B$79,$A6,'UAT cases'!$L$2:$L$79,"FAIL")
A7: Sample bank | B7: =COUNTIF('UAT cases'!$B$2:$B$79,$A7) | C7: =COUNTIFS('UAT cases'!$B$2:$B$79,$A7,'UAT cases'!$C$2:$C$79,"P1") | D7: =COUNTIFS('UAT cases'!$B$2:$B$79,$A7,'UAT cases'!$J$2:$J$79,"PASS") | E7: =COUNTIFS('UAT cases'!$B$2:$B$79,$A7,'UAT cases'!$J$2:$J$79,"FAIL") | F7: =COUNTIFS('UAT cases'!$B$2:$B$79,$A7,'UAT cases'!$J$2:$J$79,"AMBIGUOUS") | G7: =COUNTIFS('UAT cases'!$B$2:$B$79,$A7,'UAT cases'!$J$2:$J$79,"NOT RUN") | H7: =COUNTIFS('UAT cases'!$B$2:$B$79,$A7,'UAT cases'!$L$2:$L$79,"PASS") | I7: =COUNTIFS('UAT cases'!$B$2:$B$79,$A7,'UAT cases'!$L$2:$L$79,"FAIL")
A8: Data sources | B8: =COUNTIF('UAT cases'!$B$2:$B$79,$A8) | C8: =COUNTIFS('UAT cases'!$B$2:$B$79,$A8,'UAT cases'!$C$2:$C$79,"P1") | D8: =COUNTIFS('UAT cases'!$B$2:$B$79,$A8,'UAT cases'!$J$2:$J$79,"PASS") | E8: =COUNTIFS('UAT cases'!$B$2:$B$79,$A8,'UAT cases'!$J$2:$J$79,"FAIL") | F8: =COUNTIFS('UAT cases'!$B$2:$B$79,$A8,'UAT cases'!$J$2:$J$79,"AMBIGUOUS") | G8: =COUNTIFS('UAT cases'!$B$2:$B$79,$A8,'UAT cases'!$J$2:$J$79,"NOT RUN") | H8: =COUNTIFS('UAT cases'!$B$2:$B$79,$A8,'UAT cases'!$L$2:$L$79,"PASS") | I8: =COUNTIFS('UAT cases'!$B$2:$B$79,$A8,'UAT cases'!$L$2:$L$79,"FAIL")
A9: Discovery | B9: =COUNTIF('UAT cases'!$B$2:$B$79,$A9) | C9: =COUNTIFS('UAT cases'!$B$2:$B$79,$A9,'UAT cases'!$C$2:$C$79,"P1") | D9: =COUNTIFS('UAT cases'!$B$2:$B$79,$A9,'UAT cases'!$J$2:$J$79,"PASS") | E9: =COUNTIFS('UAT cases'!$B$2:$B$79,$A9,'UAT cases'!$J$2:$J$79,"FAIL") | F9: =COUNTIFS('UAT cases'!$B$2:$B$79,$A9,'UAT cases'!$J$2:$J$79,"AMBIGUOUS") | G9: =COUNTIFS('UAT cases'!$B$2:$B$79,$A9,'UAT cases'!$J$2:$J$79,"NOT RUN") | H9: =COUNTIFS('UAT cases'!$B$2:$B$79,$A9,'UAT cases'!$L$2:$L$79,"PASS") | I9: =COUNTIFS('UAT cases'!$B$2:$B$79,$A9,'UAT cases'!$L$2:$L$79,"FAIL")
A10: Onboarding | B10: =COUNTIF('UAT cases'!$B$2:$B$79,$A10) | C10: =COUNTIFS('UAT cases'!$B$2:$B$79,$A10,'UAT cases'!$C$2:$C$79,"P1") | D10: =COUNTIFS('UAT cases'!$B$2:$B$79,$A10,'UAT cases'!$J$2:$J$79,"PASS") | E10: =COUNTIFS('UAT cases'!$B$2:$B$79,$A10,'UAT cases'!$J$2:$J$79,"FAIL") | F10: =COUNTIFS('UAT cases'!$B$2:$B$79,$A10,'UAT cases'!$J$2:$J$79,"AMBIGUOUS") | G10: =COUNTIFS('UAT cases'!$B$2:$B$79,$A10,'UAT cases'!$J$2:$J$79,"NOT RUN") | H10: =COUNTIFS('UAT cases'!$B$2:$B$79,$A10,'UAT cases'!$L$2:$L$79,"PASS") | I10: =COUNTIFS('UAT cases'!$B$2:$B$79,$A10,'UAT cases'!$L$2:$L$79,"FAIL")
A11: Review | B11: =COUNTIF('UAT cases'!$B$2:$B$79,$A11) | C11: =COUNTIFS('UAT cases'!$B$2:$B$79,$A11,'UAT cases'!$C$2:$C$79,"P1") | D11: =COUNTIFS('UAT cases'!$B$2:$B$79,$A11,'UAT cases'!$J$2:$J$79,"PASS") | E11: =COUNTIFS('UAT cases'!$B$2:$B$79,$A11,'UAT cases'!$J$2:$J$79,"FAIL") | F11: =COUNTIFS('UAT cases'!$B$2:$B$79,$A11,'UAT cases'!$J$2:$J$79,"AMBIGUOUS") | G11: =COUNTIFS('UAT cases'!$B$2:$B$79,$A11,'UAT cases'!$J$2:$J$79,"NOT RUN") | H11: =COUNTIFS('UAT cases'!$B$2:$B$79,$A11,'UAT cases'!$L$2:$L$79,"PASS") | I11: =COUNTIFS('UAT cases'!$B$2:$B$79,$A11,'UAT cases'!$L$2:$L$79,"FAIL")
A12: Data changes | B12: =COUNTIF('UAT cases'!$B$2:$B$79,$A12) | C12: =COUNTIFS('UAT cases'!$B$2:$B$79,$A12,'UAT cases'!$C$2:$C$79,"P1") | D12: =COUNTIFS('UAT cases'!$B$2:$B$79,$A12,'UAT cases'!$J$2:$J$79,"PASS") | E12: =COUNTIFS('UAT cases'!$B$2:$B$79,$A12,'UAT cases'!$J$2:$J$79,"FAIL") | F12: =COUNTIFS('UAT cases'!$B$2:$B$79,$A12,'UAT cases'!$J$2:$J$79,"AMBIGUOUS") | G12: =COUNTIFS('UAT cases'!$B$2:$B$79,$A12,'UAT cases'!$J$2:$J$79,"NOT RUN") | H12: =COUNTIFS('UAT cases'!$B$2:$B$79,$A12,'UAT cases'!$L$2:$L$79,"PASS") | I12: =COUNTIFS('UAT cases'!$B$2:$B$79,$A12,'UAT cases'!$L$2:$L$79,"FAIL")
A13: Ask | B13: =COUNTIF('UAT cases'!$B$2:$B$79,$A13) | C13: =COUNTIFS('UAT cases'!$B$2:$B$79,$A13,'UAT cases'!$C$2:$C$79,"P1") | D13: =COUNTIFS('UAT cases'!$B$2:$B$79,$A13,'UAT cases'!$J$2:$J$79,"PASS") | E13: =COUNTIFS('UAT cases'!$B$2:$B$79,$A13,'UAT cases'!$J$2:$J$79,"FAIL") | F13: =COUNTIFS('UAT cases'!$B$2:$B$79,$A13,'UAT cases'!$J$2:$J$79,"AMBIGUOUS") | G13: =COUNTIFS('UAT cases'!$B$2:$B$79,$A13,'UAT cases'!$J$2:$J$79,"NOT RUN") | H13: =COUNTIFS('UAT cases'!$B$2:$B$79,$A13,'UAT cases'!$L$2:$L$79,"PASS") | I13: =COUNTIFS('UAT cases'!$B$2:$B$79,$A13,'UAT cases'!$L$2:$L$79,"FAIL")
A14: Ask (own words) | B14: =COUNTIF('UAT cases'!$B$2:$B$79,$A14) | C14: =COUNTIFS('UAT cases'!$B$2:$B$79,$A14,'UAT cases'!$C$2:$C$79,"P1") | D14: =COUNTIFS('UAT cases'!$B$2:$B$79,$A14,'UAT cases'!$J$2:$J$79,"PASS") | E14: =COUNTIFS('UAT cases'!$B$2:$B$79,$A14,'UAT cases'!$J$2:$J$79,"FAIL") | F14: =COUNTIFS('UAT cases'!$B$2:$B$79,$A14,'UAT cases'!$J$2:$J$79,"AMBIGUOUS") | G14: =COUNTIFS('UAT cases'!$B$2:$B$79,$A14,'UAT cases'!$J$2:$J$79,"NOT RUN") | H14: =COUNTIFS('UAT cases'!$B$2:$B$79,$A14,'UAT cases'!$L$2:$L$79,"PASS") | I14: =COUNTIFS('UAT cases'!$B$2:$B$79,$A14,'UAT cases'!$L$2:$L$79,"FAIL")
A15: AI agents | B15: =COUNTIF('UAT cases'!$B$2:$B$79,$A15) | C15: =COUNTIFS('UAT cases'!$B$2:$B$79,$A15,'UAT cases'!$C$2:$C$79,"P1") | D15: =COUNTIFS('UAT cases'!$B$2:$B$79,$A15,'UAT cases'!$J$2:$J$79,"PASS") | E15: =COUNTIFS('UAT cases'!$B$2:$B$79,$A15,'UAT cases'!$J$2:$J$79,"FAIL") | F15: =COUNTIFS('UAT cases'!$B$2:$B$79,$A15,'UAT cases'!$J$2:$J$79,"AMBIGUOUS") | G15: =COUNTIFS('UAT cases'!$B$2:$B$79,$A15,'UAT cases'!$J$2:$J$79,"NOT RUN") | H15: =COUNTIFS('UAT cases'!$B$2:$B$79,$A15,'UAT cases'!$L$2:$L$79,"PASS") | I15: =COUNTIFS('UAT cases'!$B$2:$B$79,$A15,'UAT cases'!$L$2:$L$79,"FAIL")
A16: Safety | B16: =COUNTIF('UAT cases'!$B$2:$B$79,$A16) | C16: =COUNTIFS('UAT cases'!$B$2:$B$79,$A16,'UAT cases'!$C$2:$C$79,"P1") | D16: =COUNTIFS('UAT cases'!$B$2:$B$79,$A16,'UAT cases'!$J$2:$J$79,"PASS") | E16: =COUNTIFS('UAT cases'!$B$2:$B$79,$A16,'UAT cases'!$J$2:$J$79,"FAIL") | F16: =COUNTIFS('UAT cases'!$B$2:$B$79,$A16,'UAT cases'!$J$2:$J$79,"AMBIGUOUS") | G16: =COUNTIFS('UAT cases'!$B$2:$B$79,$A16,'UAT cases'!$J$2:$J$79,"NOT RUN") | H16: =COUNTIFS('UAT cases'!$B$2:$B$79,$A16,'UAT cases'!$L$2:$L$79,"PASS") | I16: =COUNTIFS('UAT cases'!$B$2:$B$79,$A16,'UAT cases'!$L$2:$L$79,"FAIL")
... A18: Screens | B18: =COUNTIF('UAT cases'!$B$2:$B$79,$A18) | C18: =COUNTIFS('UAT cases'!$B$2:$B$79,$A18,'UAT cases'!$C$2:$C$79,"P1") | D18: =COUNTIFS('UAT cases'!$B$2:$B$79,$A18,'UAT cases'!$J$2:$J$79,"PASS") | E18: =COUNTIFS('UAT cases'!$B$2:$B$79,$A18,'UAT cases'!$J$2:$J$79,"FAIL") | F18: =COUNTIFS('UAT cases'!$B$2:$B$79,$A18,'UAT cases'!$J$2:$J$79,"AMBIGUOUS") | G18: =COUNTIFS('UAT cases'!$B$2:$B$79,$A18,'UAT cases'!$J$2:$J$79,"NOT RUN") | H18: =COUNTIFS('UAT cases'!$B$2:$B$79,$A18,'UAT cases'!$L$2:$L$79,"PASS") | I18: =COUNTIFS('UAT cases'!$B$2:$B$79,$A18,'UAT cases'!$L$2:$L$79,"FAIL")
A19: Total | B19: =SUM(B5:B18) | C19: =SUM(C5:C18) | D19: =SUM(D5:D18) | E19: =SUM(E5:E18) | F19: =SUM(F5:F18) | G19: =SUM(G5:G18) | H19: =SUM(H5:H18) | I19: =SUM(I5:I18)
A21: Release check
A22: P1 cases decided PASS | B22: =SUMPRODUCT(('UAT cases'!$C$2:$C$79="P1")*((('UAT cases'!$L$2:$L$79="PASS"))+(('UAT cases'!$L$2:$L$79="")*('UAT cases'!$J$2:$J$79="PASS"))>0))
A23: P1 cases in total | B23: =COUNTIF('UAT cases'!$C$2:$C$79,"P1")
A24: Open failures | B24: =SUMPRODUCT((('UAT cases'!$J$2:$J$79="FAIL")*('UAT cases'!$L$2:$L$79<>"PASS"))+(('UAT cases'!$L$2:$L$79="FAIL")*1)>0)
A25: Ambiguous without your verdict | B25: =SUMPRODUCT(('UAT cases'!$J$2:$J$79="AMBIGUOUS")*('UAT cases'!$L$2:$L$79=""))
A26: Ready to release | B26: =IF(AND(B22=B23,B24=0,B25=0),"YES","NO")
